{
  "id": "sa-mp api",
  "version": "1.0.0",
  "sourceUrl": "file:///C:/Users/Administrator/AppData/Local/Programs/Arizona Games Launcher/bin/arizona/moonloader/lib/SA-MP API",
  "files": [
    "init.lua",
    "kernel.lua",
    "samp\\0_3_7-R1\\enums.lua",
    "samp\\0_3_7-R1\\stActorPool.lua",
    "samp\\0_3_7-R1\\stChatEntry.lua",
    "samp\\0_3_7-R1\\stChatInfo.lua",
    "samp\\0_3_7-R1\\stDialogInfo.lua",
    "samp\\0_3_7-R1\\stFontRenderer.lua",
    "samp\\0_3_7-R1\\stGameInfo.lua",
    "samp\\0_3_7-R1\\stGangzone.lua",
    "samp\\0_3_7-R1\\stGangzonePool.lua",
    "samp\\0_3_7-R1\\stInputInfo.lua",
    "samp\\0_3_7-R1\\stKillEntry.lua",
    "samp\\0_3_7-R1\\stKillInfo.lua",
    "samp\\0_3_7-R1\\stLocalPlayer.lua",
    "samp\\0_3_7-R1\\stObject.lua",
    "samp\\0_3_7-R1\\stObjectPool.lua",
    "samp\\0_3_7-R1\\stPickup.lua",
    "samp\\0_3_7-R1\\stPickupPool.lua",
    "samp\\0_3_7-R1\\stPlayerPool.lua",
    "samp\\0_3_7-R1\\stRemotePlayer.lua",
    "samp\\0_3_7-R1\\stSAMP.lua",
    "samp\\0_3_7-R1\\stSAMPEntity.lua",
    "samp\\0_3_7-R1\\stSAMPPed.lua",
    "samp\\0_3_7-R1\\stSAMPPools.lua",
    "samp\\0_3_7-R1\\stSAMPVehicle.lua",
    "samp\\0_3_7-R1\\stScoreboardInfo.lua",
    "samp\\0_3_7-R1\\stServerInfo.lua",
    "samp\\0_3_7-R1\\stServerPresets.lua",
    "samp\\0_3_7-R1\\stTextLabel.lua",
    "samp\\0_3_7-R1\\stTextLabelPool.lua",
    "samp\\0_3_7-R1\\stTextdraw.lua",
    "samp\\0_3_7-R1\\stTextdrawPool.lua",
    "samp\\0_3_7-R1\\stVehiclePool.lua",
    "samp\\0_3_7-R1\\sync.lua",
    "samp\\0_3_DL-R1\\enums.lua",
    "samp\\0_3_DL-R1\\stActorPool.lua",
    "samp\\0_3_DL-R1\\stChatEntry.lua",
    "samp\\0_3_DL-R1\\stChatInfo.lua",
    "samp\\0_3_DL-R1\\stDialogInfo.lua",
    "samp\\0_3_DL-R1\\stFontRenderer.lua",
    "samp\\0_3_DL-R1\\stGameInfo.lua",
    "samp\\0_3_DL-R1\\stGangzone.lua",
    "samp\\0_3_DL-R1\\stGangzonePool.lua",
    "samp\\0_3_DL-R1\\stInputInfo.lua",
    "samp\\0_3_DL-R1\\stKillEntry.lua",
    "samp\\0_3_DL-R1\\stKillInfo.lua",
    "samp\\0_3_DL-R1\\stLocalPlayer.lua",
    "samp\\0_3_DL-R1\\stObject.lua",
    "samp\\0_3_DL-R1\\stObjectPool.lua",
    "samp\\0_3_DL-R1\\stPickup.lua",
    "samp\\0_3_DL-R1\\stPickupPool.lua",
    "samp\\0_3_DL-R1\\stPlayerPool.lua",
    "samp\\0_3_DL-R1\\stRemotePlayer.lua",
    "samp\\0_3_DL-R1\\stSAMP.lua",
    "samp\\0_3_DL-R1\\stSAMPEntity.lua",
    "samp\\0_3_DL-R1\\stSAMPPed.lua",
    "samp\\0_3_DL-R1\\stSAMPPools.lua",
    "samp\\0_3_DL-R1\\stSAMPVehicle.lua",
    "samp\\0_3_DL-R1\\stScoreboardInfo.lua",
    "samp\\0_3_DL-R1\\stServerInfo.lua",
    "samp\\0_3_DL-R1\\stServerPresets.lua",
    "samp\\0_3_DL-R1\\stSpawnInfo.lua",
    "samp\\0_3_DL-R1\\stTargetInfo.lua",
    "samp\\0_3_DL-R1\\stTextLabel.lua",
    "samp\\0_3_DL-R1\\stTextLabelPool.lua",
    "samp\\0_3_DL-R1\\stTextdraw.lua",
    "samp\\0_3_DL-R1\\stTextdrawPool.lua",
    "samp\\0_3_DL-R1\\stVehiclePool.lua",
    "samp\\0_3_DL-R1\\sync.lua",
    "samp\\definitions.lua"
  ],
  "dependencies": {
    "ffi": "1.0.0"
  }
}